woothee/__init__.py
woothee/__init__.pyi
woothee/appliance.py
woothee/appliance.pyi
woothee/browser.py
woothee/browser.pyi
woothee/crawler.py
woothee/crawler.pyi
woothee/dataset.py
woothee/dataset.pyi
woothee/misc.py
woothee/misc.pyi
woothee/mobilephone.py
woothee/mobilephone.pyi
woothee/os.py
woothee/os.pyi
woothee/py.typed
woothee/util.py
woothee/util.pyi
woothee-1.10.1.dist-info/METADATA
woothee-1.10.1.dist-info/WHEEL
woothee-1.10.1.dist-info/top_level.txt
woothee-1.10.1.dist-info/RECORD
