Metadata-Version: 1.1
Name: woothee
Version: 1.10.1
Summary: Cross-language UserAgent classifier library, python implementation
Home-page: https://github.com/woothee/woothee-python
Author: tell-k
Author-email: ffk2005@gmail.com
License: Apache License 2.0
Keywords: web,user-agent,parser
Platform: any
Classifier: Development Status :: 5 - Production/Stable
Classifier: Environment :: Web Environment
Classifier: Intended Audience :: Developers
Classifier: License :: OSI Approved :: Apache Software License
Classifier: Operating System :: OS Independent
Classifier: Programming Language :: Python
Classifier: Programming Language :: Python :: 2
Classifier: Programming Language :: Python :: 2.7
Classifier: Programming Language :: Python :: 3
Classifier: Programming Language :: Python :: 3.5
Classifier: Programming Language :: Python :: 3.6
Classifier: Programming Language :: Python :: 3.7
Classifier: Topic :: Internet :: WWW/HTTP
Classifier: Topic :: Software Development :: Libraries :: Python Modules
